autowisp-1.0.10.dist-info/METADATA
autowisp-1.0.10.dist-info/WHEEL
autowisp-1.0.10.dist-info/entry_points.txt
autowisp-1.0.10.dist-info/LICENSE
autowisp/__init__.py
autowisp/bui_util.py
autowisp/catalog.py
autowisp/evaluator.py
autowisp/file_utilities.py
autowisp/fits_utilities.py
autowisp/hdf5_file.py
autowisp/image_smoothing.py
autowisp/image_utilities.py
autowisp/iterative_rejection_util.py
autowisp/miscellaneous.py
autowisp/multiprocessing_util.py
autowisp/piecewise_bicubic_psf_map.py
autowisp/pipeline_exceptions.py
autowisp/processor.py
autowisp/run_pipeline.py
autowisp/source_finder.py
autowisp/source_finder_util.py
autowisp/split_sources.py
autowisp/tess_interface.py
autowisp/astrometry/__init__.py
autowisp/astrometry/anmatch_transformation.py
autowisp/astrometry/astrometry.py
autowisp/astrometry/astrometry_max_mag_estimate.py
autowisp/astrometry/astrometry_net_client.py
autowisp/astrometry/healpix_utilities.py
autowisp/astrometry/map_projections.py
autowisp/astrometry/transformation.py
autowisp/browser_interface/__init__.py
autowisp/browser_interface/manage.py
autowisp/browser_interface/set_project_middleware.py
autowisp/browser_interface/start.py
autowisp/browser_interface/configuration/__init__.py
autowisp/browser_interface/configuration/admin.py
autowisp/browser_interface/configuration/apps.py
autowisp/browser_interface/configuration/models.py
autowisp/browser_interface/configuration/urls.py
autowisp/browser_interface/configuration/views.py
autowisp/browser_interface/configuration/migrations/__init__.py
autowisp/browser_interface/configuration/static/configuration/css/config_tree.css
autowisp/browser_interface/configuration/static/configuration/css/jquery.orgchart.css
autowisp/browser_interface/configuration/static/configuration/css/survey.css
autowisp/browser_interface/configuration/static/configuration/js/autowisp.config.tree.js
autowisp/browser_interface/configuration/templates/configuration/config_tree.html
autowisp/browser_interface/configuration/templates/configuration/edit_survey.html
autowisp/browser_interface/configuration/templates/configuration/survey_class_entries.html
autowisp-1.0.10.dist-info/RECORD
