Metadata-Version: 2.1
Name: autowisp
Version: 1.0.10
Summary: Pipeline for extracting photometry from wide-field night sky images
Author-Email: Kaloyan Penev <Kaloyan.Penev@utdallas.edu>, Angel Romero <Angel.Romero@utdallas.edu>, Ashkan Jafarzadeh <ashkan.jafarzadeh@utdallas.edu>
Maintainer-Email: Kaloyan Penev <Kaloyan.Penev@utdallas.edu>, Angel Romero <Angel.Romero@utdallas.edu>, Ashkan Jafarzadeh <ashkan.jafarzadeh@utdallas.edu>
License: MIT License
Classifier: Development Status :: 4 - Beta
Classifier: Environment :: Console
Classifier: Operating System :: Microsoft :: Windows
Classifier: Operating System :: MacOS
Classifier: Operating System :: POSIX :: Linux
Classifier: Intended Audience :: Developers
Classifier: Intended Audience :: Science/Research
Classifier: License :: OSI Approved :: MIT License
Classifier: Programming Language :: C++
Classifier: Programming Language :: C
Classifier: Programming Language :: Python :: 3
Classifier: Topic :: Scientific/Engineering :: Image Processing
Classifier: Topic :: Scientific/Engineering :: Astronomy
Classifier: Topic :: Scientific/Engineering :: Physics
Project-URL: source, https://github.com/kpenev/AutoWISP
Project-URL: documentation, https://kpenev.github.io/AutoWISP/
Requires-Python: >3.7
Requires-Dist: antlr4-python3-runtime
Requires-Dist: asteval
Requires-Dist: astropy
Requires-Dist: astroquery
Requires-Dist: astrowisp>=1.5
Requires-Dist: configargparse
Requires-Dist: Django
Requires-Dist: h5py
Requires-Dist: lxml
Requires-Dist: matplotlib
Requires-Dist: numpy<2
Requires-Dist: pandas
Requires-Dist: pillow
Requires-Dist: platformdirs
Requires-Dist: psutil
Requires-Dist: pytransit
Requires-Dist: rechunker
Requires-Dist: requests
Requires-Dist: scipy
Requires-Dist: sqlalchemy
Requires-Dist: zarr
Provides-Extra: test
Provides-Extra: browser-interface
Requires-Dist: Django; extra == "browser-interface"
